doc_insights/__init__.py
doc_insights/file_processing.py
doc_insights/link_validation.py
doc_insights/logging_utils.py
doc_insights/main.py
doc_insights/post_install.py
tests/__init__.py
tests/test_file_processing.py
tests/test_link_validation.py
tests/test_logging_utils.py
doc_insights-0.1.1.dist-info/LICENSE
doc_insights-0.1.1.dist-info/METADATA
doc_insights-0.1.1.dist-info/WHEEL
doc_insights-0.1.1.dist-info/entry_points.txt
doc_insights-0.1.1.dist-info/top_level.txt
doc_insights-0.1.1.dist-info/RECORD
