Metadata-Version: 2.1
Name: doc-insights
Version: 0.1.1
Summary: A tool for validating documentation and related resources
Home-page: https://github.com/ChrisMahlke/doc-insights
Author: Chris Mahlke
Author-email: Chris.Mahlke@c3.ai
Classifier: Programming Language :: Python :: 3
Classifier: License :: OSI Approved :: MIT License
Classifier: Operating System :: OS Independent
Requires-Python: >=3.6
License-File: LICENSE
Requires-Dist: pandas
Requires-Dist: numpy
Requires-Dist: ipython
Requires-Dist: jupyter
